{
  "key": "DRAK_Clipper_Thruster_Main_Top",
  "ref": "1e3726fc-f779-483c-898c-ecd5d24d131f",
  "category": "thrusters",
  "type": "MainThruster",
  "sub_type": null,
  "size": "1",
  "grade": "1",
  "manufacturer_ref": null,
  "name": null,
  "short_name": null,
  "description": null,
  "inventory_consumption": {
    "micro_scu": 1.0,
    "dimensions": {
      "x": 0.15,
      "y": 0.15,
      "z": 0.15
    }
  },
  "loadout": [
    {
      "name": "hardpoint_fin_inner_001",
      "min_size": "1",
      "max_size": "1",
      "types": [
        "Misc"
      ]
    },
    {
      "name": "hardpoint_fin_inner_002",
      "min_size": "1",
      "max_size": "1",
      "types": [
        "Misc"
      ]
    },
    {
      "name": "hardpoint_fin_inner_003",
      "min_size": "1",
      "max_size": "1",
      "types": [
        "Misc"
      ]
    },
    {
      "name": "hardpoint_fin_inner_004",
      "min_size": "1",
      "max_size": "1",
      "types": [
        "Misc"
      ]
    },
    {
      "name": "hardpoint_fin_inner_005",
      "min_size": "1",
      "max_size": "1",
      "types": [
        "Misc"
      ]
    },
    {
      "name": "hardpoint_fin_inner_006",
      "min_size": "1",
      "max_size": "1",
      "types": [
        "Misc"
      ]
    },
    {
      "name": "hardpoint_fin_inner_007",
      "min_size": "1",
      "max_size": "1",
      "types": [
        "Misc"
      ]
    },
    {
      "name": "hardpoint_fin_inner_008",
      "min_size": "1",
      "max_size": "1",
      "types": [
        "Misc"
      ]
    },
    {
      "name": "hardpoint_fin_inner_009",
      "min_size": "1",
      "max_size": "1",
      "types": [
        "Misc"
      ]
    },
    {
      "name": "hardpoint_fin_inner_010",
      "min_size": "1",
      "max_size": "1",
      "types": [
        "Misc"
      ]
    },
    {
      "name": "hardpoint_fin_inner_011",
      "min_size": "1",
      "max_size": "1",
      "types": [
        "Misc"
      ]
    },
    {
      "name": "hardpoint_fin_inner_012",
      "min_size": "1",
      "max_size": "1",
      "types": [
        "Misc"
      ]
    },
    {
      "name": "hardpoint_fin_inner_013",
      "min_size": "1",
      "max_size": "1",
      "types": [
        "Misc"
      ]
    },
    {
      "name": "hardpoint_fin_inner_014",
      "min_size": "1",
      "max_size": "1",
      "types": [
        "Misc"
      ]
    },
    {
      "name": "hardpoint_fin_inner_015",
      "min_size": "1",
      "max_size": "1",
      "types": [
        "Misc"
      ]
    },
    {
      "name": "hardpoint_fin_inner_016",
      "min_size": "1",
      "max_size": "1",
      "types": [
        "Misc"
      ]
    },
    {
      "name": "hardpoint_fin_outer_001",
      "min_size": "1",
      "max_size": "1",
      "types": [
        "Misc"
      ]
    },
    {
      "name": "hardpoint_fin_outer_002",
      "min_size": "1",
      "max_size": "1",
      "types": [
        "Misc"
      ]
    },
    {
      "name": "hardpoint_fin_outer_003",
      "min_size": "1",
      "max_size": "1",
      "types": [
        "Misc"
      ]
    },
    {
      "name": "hardpoint_fin_outer_004",
      "min_size": "1",
      "max_size": "1",
      "types": [
        "Misc"
      ]
    },
    {
      "name": "hardpoint_fin_outer_005",
      "min_size": "1",
      "max_size": "1",
      "types": [
        "Misc"
      ]
    },
    {
      "name": "hardpoint_fin_outer_006",
      "min_size": "1",
      "max_size": "1",
      "types": [
        "Misc"
      ]
    },
    {
      "name": "hardpoint_fin_outer_007",
      "min_size": "1",
      "max_size": "1",
      "types": [
        "Misc"
      ]
    },
    {
      "name": "hardpoint_fin_outer_008",
      "min_size": "1",
      "max_size": "1",
      "types": [
        "Misc"
      ]
    },
    {
      "name": "hardpoint_fin_outer_009",
      "min_size": "1",
      "max_size": "1",
      "types": [
        "Misc"
      ]
    },
    {
      "name": "hardpoint_fin_outer_010",
      "min_size": "1",
      "max_size": "1",
      "types": [
        "Misc"
      ]
    },
    {
      "name": "hardpoint_fin_outer_011",
      "min_size": "1",
      "max_size": "1",
      "types": [
        "Misc"
      ]
    },
    {
      "name": "hardpoint_fin_outer_012",
      "min_size": "1",
      "max_size": "1",
      "types": [
        "Misc"
      ]
    },
    {
      "name": "hardpoint_fin_outer_013",
      "min_size": "1",
      "max_size": "1",
      "types": [
        "Misc"
      ]
    },
    {
      "name": "hardpoint_fin_outer_014",
      "min_size": "1",
      "max_size": "1",
      "types": [
        "Misc"
      ]
    },
    {
      "name": "hardpoint_fin_outer_015",
      "min_size": "1",
      "max_size": "1",
      "types": [
        "Misc"
      ]
    },
    {
      "name": "hardpoint_fin_outer_016",
      "min_size": "1",
      "max_size": "1",
      "types": [
        "Misc"
      ]
    }
  ],
  "durability": {
    "health": 9100.0
  },
  "type_data": {
    "thrust_capacity": 2532544.0,
    "fuel_burn_rate_per10_k_newton": 0.125,
    "thruster_type": "Main",
    "thruster_class": "main"
  }
}