{
  "key": "ESPR_Prowler_Thruster_Retro_Utility",
  "ref": "92bedd20-a06e-4169-8fd7-0350bdbbf9cf",
  "category": "thrusters",
  "type": "ManneuverThruster",
  "sub_type": null,
  "size": "1",
  "grade": "1",
  "manufacturer_ref": null,
  "name": null,
  "short_name": null,
  "description": null,
  "inventory_consumption": {
    "micro_scu": 1.0,
    "dimensions": {
      "x": 0.15,
      "y": 0.15,
      "z": 0.15
    }
  },
  "durability": {
    "health": 18000.0
  },
  "type_data": {
    "thrust_capacity": 949184.2,
    "fuel_burn_rate_per10_k_newton": 0.1015,
    "thruster_type": "Retro",
    "thruster_class": "retro"
  }
}