{
  "key": "INTK_AEGS_Hammerhead",
  "ref": "a6e4f520-2268-4269-a61f-40df2d17a0a7",
  "category": "fuel_intakes",
  "type": "FuelIntake",
  "sub_type": "Fuel",
  "size": "1",
  "grade": "1",
  "manufacturer_ref": "cf4a74bf-eb2c-462a-9b78-f7f2724c31d2",
  "name": null,
  "short_name": null,
  "description": null,
  "inventory_consumption": {
    "micro_scu": 1.0,
    "dimensions": {
      "x": 0.1501,
      "y": 0.15,
      "z": 0.15
    }
  },
  "type_data": {
    "fuel_push_rate": 0.0,
    "minimum_rate": 0.1
  }
}