{
  "key": "MRCK_S03_VNCL_Quad_S01",
  "ref": "c5660ffe-d8db-4452-ba69-4b519599c445",
  "category": "missile_racks",
  "type": "MissileLauncher",
  "sub_type": "MissileRack",
  "size": "3",
  "grade": "1",
  "manufacturer_ref": "4668760a-d8a1-48d0-be4d-42304b702de0",
  "name": "Vanduul S3 Quad Missile Rack",
  "short_name": null,
  "description": null,
  "inventory_consumption": {
    "micro_scu": 756000.0,
    "dimensions": {
      "x": 0.6699014,
      "y": 4.422015,
      "z": 1.202842
    }
  },
  "loadout": [
    {
      "name": "missile_01_attach",
      "min_size": "1",
      "max_size": "1",
      "types": [
        "Missile"
      ]
    },
    {
      "name": "missile_02_attach",
      "min_size": "1",
      "max_size": "1",
      "types": [
        "Missile"
      ]
    },
    {
      "name": "missile_03_attach",
      "min_size": "1",
      "max_size": "1",
      "types": [
        "Missile"
      ]
    },
    {
      "name": "missile_04_attach",
      "min_size": "1",
      "max_size": "1",
      "types": [
        "Missile"
      ]
    }
  ],
  "durability": {
    "health": 200.0
  }
}