{
  "key": "MISC_Starlancer_CargoGrid_Small_Template",
  "ref": "cdb85e74-2cc2-4faf-a0a8-fb6cf931dacd",
  "category": "inventory",
  "type": "CargoGrid",
  "type_data": {
    "dimensions": {
      "x": 2.5,
      "y": 5.0,
      "z": 2.5
    },
    "capacity": 16.0,
    "max_container_size": {
      "size": 16,
      "dimensions": {
        "x": 5.0,
        "y": 2.5,
        "z": 2.5
      }
    },
    "limits": {
      "min": {
        "dimensions": {
          "x": 1.25,
          "y": 1.25,
          "z": 1.25
        },
        "capacity": 1.0
      },
      "max": {
        "dimensions": {
          "x": 2.5,
          "y": 5.0,
          "z": 2.5
        },
        "capacity": 16.0
      }
    }
  }
}