{
  "key": "Paint_Mustang_Delta_NineTails",
  "ref": "8b2e5ff0-ee59-41c6-b4dd-5606bc7cce3c",
  "category": "paints",
  "type": "Paints",
  "sub_type": null,
  "size": "1",
  "grade": "1",
  "manufacturer_ref": "ec227ef3-fb08-4897-abdb-579eb4e87c25",
  "name": "Mustang Delta Livery",
  "short_name": null,
  "description": "Standard livery for the C.O. Mustang Delta.",
  "inventory_consumption": {
    "micro_scu": 24000.0,
    "dimensions": {
      "x": 0.3,
      "y": 0.4,
      "z": 0.2
    }
  }
}